tksheet/__init__.py
tksheet/colors.py
tksheet/column_headers.py
tksheet/constants.py
tksheet/find_window.py
tksheet/formatters.py
tksheet/functions.py
tksheet/main_table.py
tksheet/menus.py
tksheet/other_classes.py
tksheet/row_index.py
tksheet/sheet.py
tksheet/sheet_options.py
tksheet/sorting.py
tksheet/text_editor.py
tksheet/themes.py
tksheet/tksheet_types.py
tksheet/tooltip.py
tksheet/top_left_rectangle.py
tksheet-7.5.17.dist-info/licenses/LICENSE.txt
tksheet-7.5.17.dist-info/METADATA
tksheet-7.5.17.dist-info/WHEEL
tksheet-7.5.17.dist-info/top_level.txt
tksheet-7.5.17.dist-info/RECORD
