Metadata-Version: 2.4
Name: tksheet
Version: 7.5.17
Summary: Tkinter table / sheet and treeview widget
Author-email: ragardner <github@ragardner.simplelogin.com>
License: Copyright (c) 2019 ragardner and open source contributors
Project-URL: Homepage, https://github.com/ragardner/tksheet
Project-URL: Documentation, https://github.com/ragardner/tksheet/wiki/Version-7
Project-URL: Changelog, https://github.com/ragardner/tksheet/blob/master/docs/CHANGELOG.md
Project-URL: Issues, https://github.com/ragardner/tksheet/issues
Project-URL: Funding, https://github.com/ragardner
Keywords: tkinter,table,widget,tree,treeview,sheet,grid,tk
Classifier: Development Status :: 5 - Production/Stable
Classifier: Intended Audience :: Developers
Classifier: Topic :: Software Development :: Libraries
Classifier: License :: OSI Approved :: MIT License
Classifier: Programming Language :: Python :: 3.8
Classifier: Programming Language :: Python :: 3.9
Classifier: Programming Language :: Python :: 3.10
Classifier: Programming Language :: Python :: 3.11
Classifier: Programming Language :: Python :: 3.12
Classifier: Programming Language :: Python :: 3.13
Requires-Python: >=3.8
License-File: LICENSE.txt
Dynamic: license-file
